smollama_py/__init__.py
smollama_py/__main__.py
smollama_py/cli.py
smollama_py/public/icon-16x16.png
smollama_py/public/index.html
smollama_py/public/smollama.css
smollama_py/public/katex/katex.min.css
smollama_py/public/katex/katex.min.js
smollama_py/public/katex/fonts/KaTeX_AMS-Regular.ttf
smollama_py/public/katex/fonts/KaTeX_AMS-Regular.woff
smollama_py/public/katex/fonts/KaTeX_AMS-Regular.woff2
smollama_py/public/katex/fonts/KaTeX_Caligraphic-Bold.ttf
smollama_py/public/katex/fonts/KaTeX_Caligraphic-Bold.woff
smollama_py/public/katex/fonts/KaTeX_Caligraphic-Bold.woff2
smollama_py/public/katex/fonts/KaTeX_Caligraphic-Regular.ttf
smollama_py/public/katex/fonts/KaTeX_Caligraphic-Regular.woff
smollama_py/public/katex/fonts/KaTeX_Caligraphic-Regular.woff2
smollama_py/public/katex/fonts/KaTeX_Fraktur-Bold.ttf
smollama_py/public/katex/fonts/KaTeX_Fraktur-Bold.woff
smollama_py/public/katex/fonts/KaTeX_Fraktur-Bold.woff2
smollama_py/public/katex/fonts/KaTeX_Fraktur-Regular.ttf
smollama_py/public/katex/fonts/KaTeX_Fraktur-Regular.woff
smollama_py/public/katex/fonts/KaTeX_Fraktur-Regular.woff2
smollama_py/public/katex/fonts/KaTeX_Main-Bold.ttf
smollama_py/public/katex/fonts/KaTeX_Main-Bold.woff
smollama_py/public/katex/fonts/KaTeX_Main-Bold.woff2
smollama_py/public/katex/fonts/KaTeX_Main-BoldItalic.ttf
smollama_py/public/katex/fonts/KaTeX_Main-BoldItalic.woff
smollama_py/public/katex/fonts/KaTeX_Main-BoldItalic.woff2
smollama_py/public/katex/fonts/KaTeX_Main-Italic.ttf
smollama_py/public/katex/fonts/KaTeX_Main-Italic.woff
smollama_py/public/katex/fonts/KaTeX_Main-Italic.woff2
smollama_py/public/katex/fonts/KaTeX_Main-Regular.ttf
smollama_py/public/katex/fonts/KaTeX_Main-Regular.woff
smollama_py/public/katex/fonts/KaTeX_Main-Regular.woff2
smollama_py/public/katex/fonts/KaTeX_Math-BoldItalic.ttf
smollama_py/public/katex/fonts/KaTeX_Math-BoldItalic.woff
smollama_py/public/katex/fonts/KaTeX_Math-BoldItalic.woff2
smollama_py/public/katex/fonts/KaTeX_Math-Italic.ttf
smollama_py-0.0.2.dist-info/licenses/LICENSE
smollama_py-0.0.2.dist-info/METADATA
smollama_py-0.0.2.dist-info/WHEEL
smollama_py-0.0.2.dist-info/entry_points.txt
smollama_py-0.0.2.dist-info/top_level.txt
smollama_py-0.0.2.dist-info/RECORD
