Metadata-Version: 2.4
Name: smollama-py
Version: 0.0.2
Summary: A python app to serve smOllama
Author: Sukhbinder Singh
License: Apache-2.0
Project-URL: Homepage, https://github.com/sukhbinder/smollama-py
Project-URL: Changelog, https://github.com/sukhbinder/smollama-py/releases
Project-URL: Issues, https://github.com/sukhbinder/smollama-py/issues
Project-URL: CI, https://github.com/sukhbinder/smollama-py/actions
Classifier: License :: OSI Approved :: Apache Software License
Requires-Python: >=3.8
License-File: LICENSE
Requires-Dist: eel
Provides-Extra: test
Requires-Dist: pytest; extra == "test"
Dynamic: license-file
